wmempy/__init__.py
wmempy/__main__.py
wmempy/wmem_cli.py
wmempy/wmem_memory.py
wmempy/wmem_process.py
wmempy/wmem_scannable.py
wmempy/wmem_scanner.py
wmempy/wmem_structs.py
wmempy/wmem_system.py
wmempy-0.1.2.dist-info/LICENSE
wmempy-0.1.2.dist-info/METADATA
wmempy-0.1.2.dist-info/WHEEL
wmempy-0.1.2.dist-info/entry_points.txt
wmempy-0.1.2.dist-info/top_level.txt
wmempy-0.1.2.dist-info/RECORD
