Metadata-Version: 2.1
Name: wmempy
Version: 0.1.2
Summary: WinApi Memory Access Application
Home-page: https://github.com/fitancinpet/WMemPy
Author: Petr Ančinec
Author-email: ancinpet@fit.cvut.cz
License: MIT License
Keywords: click,winapi,openprocess
Platform: UNKNOWN
Classifier: Intended Audience :: Developers
Classifier: License :: OSI Approved :: MIT License
Classifier: Operating System :: OS Independent
Classifier: Environment :: Console
Classifier: Natural Language :: English
Classifier: Programming Language :: Python
Classifier: Programming Language :: Python :: 3
Classifier: Programming Language :: Python :: 3.7
Classifier: Programming Language :: Python :: 3.8
Classifier: Operating System :: Microsoft
Classifier: Topic :: Software Development :: Libraries
Requires-Python: >=3.6
Requires-Dist: pywin32
Requires-Dist: click (>=6)
Requires-Dist: numpy (==1.19.3)
Requires-Dist: Cython
Provides-Extra: dev
Requires-Dist: sphinx ; extra == 'dev'
Requires-Dist: pytest ; extra == 'dev'
Requires-Dist: flexmock ; extra == 'dev'
